[{"category":"javascript","title":"Atque nemo facilis nisi adipisci excepturi.","cover":"https://striveschool.ghost.io/content/images/2020/12/M1M06-3.png","readTime":{"value":"3","unit":"minute"},"author":{"name":"Electa","avatar":"https://ui-avatars.com/api/?name=John+Doe"},"content":"<div class='py-5 blog-content'>Earum aut veritatis quis quos beatae. Ea qui est sunt cum. Minima omnis voluptatem. Mollitia amet doloribus placeat aut. Ab vel reprehenderit quis dolorem voluptatem est saepe sapiente nihil. Omnis occaecati quo quidem quibusdam quia.</div>","createdAt":"2022-03-02T15:39:49.310Z","id":"cvddezcl09q5y9r"}]